translators/__init__.py
translators/apis.py
translators/test.py
translate_api-4.9.1.dist-info/LICENSE
translate_api-4.9.1.dist-info/METADATA
translate_api-4.9.1.dist-info/WHEEL
translate_api-4.9.1.dist-info/top_level.txt
translate_api-4.9.1.dist-info/RECORD
