Metadata-Version: 2.1
Name: translate-api
Version: 4.9.1
Summary: Translators is a library which aims to bring free, multiple, enjoyable translation to individuals and students in Python.
Home-page: https://github.com/uliontse/translators
Author: UlionTse
Author-email: shinalone@outlook.com
License: MIT
Keywords: translate,translator,fanyi,translate_html,Google,Yandex,Bing,Baidu,Alibaba,Tencent,Youdao,Sogou,Deepl,Caiyun
Platform: UNKNOWN
Classifier: Development Status :: 5 - Production/Stable
Classifier: Environment :: Web Environment
Classifier: Intended Audience :: Developers
Classifier: License :: OSI Approved :: MIT License
Classifier: Programming Language :: Python :: 3.6
Classifier: Programming Language :: Python :: 3.7
Classifier: Programming Language :: Python :: 3.8
Classifier: Programming Language :: Python :: 3.9
Requires-Dist: requests (>=2.25.1)
Requires-Dist: PyExecJS (>=1.5.1)
Requires-Dist: lxml (>=4.5.0)
Requires-Dist: loguru (>=0.4.1)
Requires-Dist: pathos (>=0.2.7)
